georender/__init__.py
georender/common.py
georender/georender.py
georender-0.0.1.dist-info/LICENSE
georender-0.0.1.dist-info/METADATA
georender-0.0.1.dist-info/WHEEL
georender-0.0.1.dist-info/entry_points.txt
georender-0.0.1.dist-info/top_level.txt
georender-0.0.1.dist-info/RECORD
